MANIFEST.in
README.md
arpy.py
setup.py
arpy.egg-info/PKG-INFO
arpy.egg-info/SOURCES.txt
arpy.egg-info/dependency_links.txt
arpy.egg-info/top_level.txt
test/bsd_mixed.ar
test/bsd_multi_names.ar
test/bsd_single_name.ar
test/contents.ar
test/empty.ar
test/gnu_mixed.ar
test/gnu_multi_names.ar
test/gnu_single_name.ar
test/msvc_lib.ar
test/normal.ar
test/sym.ar
test/test_bsd.py
test/test_contents.py
test/test_failures.py
test/test_gnu.py
test/test_normal.py
test/windows.ar